greyai_sdk/__init__.py
greyai_sdk/cli.py
greyai_sdk/dataset.py
greyai_sdk/model.py
greyai_sdk/package.py
greyai_sdk/version.py
greyai_sdk-0.0.3.dist-info/METADATA
greyai_sdk-0.0.3.dist-info/WHEEL
greyai_sdk-0.0.3.dist-info/entry_points.txt
greyai_sdk-0.0.3.dist-info/top_level.txt
greyai_sdk-0.0.3.dist-info/RECORD
