Metadata-Version: 2.1
Name: greyai-sdk
Version: 0.0.3
Summary: Grey AI Model Builder SDK
Home-page: UNKNOWN
Author: Grey Development Team
Author-email: dev@greyai.io
License: UNKNOWN
Platform: UNKNOWN
Classifier: Programming Language :: Python :: 3
Classifier: License :: OSI Approved :: MIT License
Classifier: Operating System :: OS Independent
Requires-Python: >=3
Requires-Dist: tensorflow (==2.4.1)
Requires-Dist: fastapi (==0.64.0)
Requires-Dist: pydantic (==1.8.2)
Requires-Dist: click (==8.0.1)
